{
    "id": "02217",
    "name": {
        "en": "Bjoernaengen \/ Hårbörsta"
    },
    "country": "SE",
    "region": "Z",
    "identifiers": {
        "national": null,
        "wmo": "02217",
        "ghcn": null,
        "wban": null,
        "usaf": null,
        "mosmix": null,
        "icao": null,
        "iata": null
    },
    "location": {
        "latitude": 63.3736,
        "longitude": 13.1606,
        "elevation": 435
    },
    "timezone": "Europe\/Stockholm",
    "history": []
}