{
    "id": "02991",
    "name": {
        "en": "Porvoo Emasalo \/ Boviken"
    },
    "country": "FI",
    "region": null,
    "identifiers": {
        "national": null,
        "wmo": "02991",
        "ghcn": null,
        "wban": null,
        "usaf": "029910",
        "mosmix": null,
        "icao": null,
        "iata": null
    },
    "location": {
        "latitude": 60.2,
        "longitude": 25.6333,
        "elevation": 20
    },
    "timezone": "Europe\/Helsinki",
    "history": []
}