{
    "id": "06746",
    "name": {
        "en": "Grimsel Pass \/ Räterichsboden"
    },
    "country": "CH",
    "region": "BE",
    "identifiers": {
        "national": null,
        "wmo": "06746",
        "ghcn": null,
        "wban": null,
        "usaf": null,
        "mosmix": null,
        "icao": null,
        "iata": null
    },
    "location": {
        "latitude": 46.5833,
        "longitude": 8.3333,
        "elevation": 2000
    },
    "timezone": "Europe\/Zurich",
    "history": []
}