{
    "id": "07059",
    "name": {
        "en": "Amiens \/ Bécordel-Bécourt"
    },
    "country": "FR",
    "region": "S",
    "identifiers": {
        "national": null,
        "wmo": "07059",
        "ghcn": null,
        "wban": null,
        "usaf": "070590",
        "mosmix": null,
        "icao": null,
        "iata": null
    },
    "location": {
        "latitude": 49.9719,
        "longitude": 2.7039,
        "elevation": 111
    },
    "timezone": "Europe\/Paris",
    "history": []
}