{
    "id": "16318",
    "name": {
        "en": "Martina Franca(iafb) / Masseria Orimini"
    },
    "country": "IT",
    "region": "PU",
    "identifiers": {
        "national": null,
        "wmo": "16318",
        "ghcn": null,
        "wban": null,
        "usaf": "163180",
        "mosmix": null,
        "icao": null,
        "iata": null
    },
    "location": {
        "latitude": 40.6428,
        "longitude": 17.2061,
        "elevation": 413
    },
    "timezone": "Europe/Rome",
    "history": []
}