{
    "id": "33679",
    "name": {
        "en": "Kamenka \/ Camenca"
    },
    "country": "MD",
    "region": null,
    "identifiers": {
        "national": null,
        "wmo": "33679",
        "ghcn": "MD000033679",
        "wban": null,
        "usaf": "336790",
        "mosmix": null,
        "icao": null,
        "iata": null
    },
    "location": {
        "latitude": 48.0333,
        "longitude": 28.7,
        "elevation": 154
    },
    "timezone": "Europe\/Chisinau",
    "history": []
}