{
    "id": "41764",
    "name": {
        "en": "Hyderabad Airport"
    },
    "country": "PK",
    "region": "S",
    "identifiers": {
        "national": null,
        "wmo": "41764",
        "ghcn": "PKM00041764",
        "wban": null,
        "usaf": "417640",
        "mosmix": null,
        "icao": "OPKD",
        "iata": "HDD"
    },
    "location": {
        "latitude": 25.3833,
        "longitude": 68.4167,
        "elevation": 40
    },
    "timezone": "Asia/Karachi",
    "history": []
}