{
    "id": "43588",
    "name": {
        "en": "Kaadedhdhoo \/ Thinadhoo"
    },
    "country": "MV",
    "region": null,
    "identifiers": {
        "national": null,
        "wmo": "43588",
        "ghcn": null,
        "wban": null,
        "usaf": "435880",
        "mosmix": null,
        "icao": null,
        "iata": null
    },
    "location": {
        "latitude": 0.4883,
        "longitude": 72.9961,
        "elevation": 1
    },
    "timezone": "Indian\/Maldives",
    "history": []
}