{
    "id": "48409",
    "name": {
        "en": "Sisaket Agromet \/ Ban Nong Yang"
    },
    "country": "TH",
    "region": null,
    "identifiers": {
        "national": null,
        "wmo": "48409",
        "ghcn": null,
        "wban": null,
        "usaf": "484090",
        "mosmix": null,
        "icao": null,
        "iata": null
    },
    "location": {
        "latitude": 15.0853,
        "longitude": 104.3306,
        "elevation": 127
    },
    "timezone": "Asia\/Bangkok",
    "history": []
}