{
    "id": "63791",
    "name": {
        "en": "Kilimanjaro Airport"
    },
    "country": "TZ",
    "region": "AR",
    "identifiers": {
        "national": null,
        "wmo": "63791",
        "ghcn": "TZ000063791",
        "wban": null,
        "usaf": "637910",
        "mosmix": "63791",
        "icao": "HTKJ",
        "iata": "JRO"
    },
    "location": {
        "latitude": -3.4167,
        "longitude": 37.0667,
        "elevation": 891
    },
    "timezone": "Africa\/Dar_es_Salaam",
    "history": []
}