{
    "id": "64247",
    "name": {
        "en": "Mbuji-Mayi"
    },
    "country": "CD",
    "region": "KE",
    "identifiers": {
        "national": null,
        "wmo": "64247",
        "ghcn": "CGM00064247",
        "wban": null,
        "usaf": "641556",
        "mosmix": null,
        "icao": "FZWA",
        "iata": "MJM"
    },
    "location": {
        "latitude": -6.1667,
        "longitude": 23.6167,
        "elevation": 633
    },
    "timezone": "Africa\/Lubumbashi",
    "history": []
}