{
    "id": "68443",
    "name": {
        "en": "Bloemfontein City \/ Universitas"
    },
    "country": "ZA",
    "region": "FS",
    "identifiers": {
        "national": null,
        "wmo": "68443",
        "ghcn": null,
        "wban": null,
        "usaf": null,
        "mosmix": null,
        "icao": null,
        "iata": null
    },
    "location": {
        "latitude": -29.1169,
        "longitude": 26.1831,
        "elevation": 1406
    },
    "timezone": "Africa\/Johannesburg",
    "history": []
}