{
    "id": "71133",
    "name": {
        "en": "Spiritwood West, Sask"
    },
    "country": "CA",
    "region": "SK",
    "identifiers": {
        "national": null,
        "wmo": "71133",
        "ghcn": "CA004067723",
        "wban": null,
        "usaf": "711330",
        "mosmix": null,
        "icao": "CWSR",
        "iata": null
    },
    "location": {
        "latitude": 53.3667,
        "longitude": -107.55,
        "elevation": 584
    },
    "timezone": "America\/Regina",
    "history": []
}