{
    "id": "71163",
    "name": {
        "en": "Lac La Martre"
    },
    "country": "CA",
    "region": "NT",
    "identifiers": {
        "national": null,
        "wmo": "71163",
        "ghcn": "CA002202678",
        "wban": null,
        "usaf": "711630",
        "mosmix": null,
        "icao": "CWMT",
        "iata": null
    },
    "location": {
        "latitude": 63.15,
        "longitude": -117.2667,
        "elevation": 271
    },
    "timezone": "America/Yellowknife",
    "history": []
}