{
    "id": "71167",
    "name": {
        "en": "Porter Lake"
    },
    "country": "CA",
    "region": "NT",
    "identifiers": {
        "national": null,
        "wmo": "71167",
        "ghcn": "CA003062239",
        "wban": null,
        "usaf": "711670",
        "mosmix": null,
        "icao": "CWJP",
        "iata": null
    },
    "location": {
        "latitude": 61.6667,
        "longitude": -108.4167,
        "elevation": 396
    },
    "timezone": "America\/Yellowknife",
    "history": []
}