{
    "id": "71313",
    "name": {
        "en": "Havre St Pierre"
    },
    "country": "CA",
    "region": "QC",
    "identifiers": {
        "national": null,
        "wmo": "71313",
        "ghcn": "CA007043018",
        "wban": null,
        "usaf": "713130",
        "mosmix": null,
        "icao": "CYGV",
        "iata": "YGV"
    },
    "location": {
        "latitude": 50.2833,
        "longitude": -63.6167,
        "elevation": 33
    },
    "timezone": "America/Montreal",
    "history": []
}