{
    "id": "71406",
    "name": {
        "en": "Ferolle Point / Shoal Cove"
    },
    "country": "CA",
    "region": "NF",
    "identifiers": {
        "national": null,
        "wmo": "71406",
        "ghcn": "CA008401565",
        "wban": null,
        "usaf": "714060",
        "mosmix": null,
        "icao": "CWXI",
        "iata": null
    },
    "location": {
        "latitude": 51.0167,
        "longitude": -57.1,
        "elevation": 6
    },
    "timezone": "America/St_Johns",
    "history": []
}