{
    "id": "71738",
    "name": {
        "en": "Wawa, Ontario"
    },
    "country": "CA",
    "region": "ON",
    "identifiers": {
        "national": null,
        "wmo": "71738",
        "ghcn": "CA006059D09",
        "wban": null,
        "usaf": "717380",
        "mosmix": null,
        "icao": "CYXZ",
        "iata": "YXZ"
    },
    "location": {
        "latitude": 47.9667,
        "longitude": -84.7833,
        "elevation": 287
    },
    "timezone": "America\/Toronto",
    "history": []
}