{
    "id": "72374",
    "name": {
        "en": "Winslow Municipal Airport"
    },
    "country": "US",
    "region": "AZ",
    "identifiers": {
        "national": null,
        "wmo": "72374",
        "ghcn": "USW00023194",
        "wban": "23194",
        "usaf": "723740",
        "mosmix": "72374",
        "icao": "KINW",
        "iata": "INW"
    },
    "location": {
        "latitude": 35.0333,
        "longitude": -110.7167,
        "elevation": 1505
    },
    "timezone": "America/Phoenix",
    "history": []
}