{
    "id": "72394",
    "name": {
        "en": "Santa Maria Public Airport"
    },
    "country": "US",
    "region": "CA",
    "identifiers": {
        "national": null,
        "wmo": "72394",
        "ghcn": "USW00023273",
        "wban": "23273",
        "usaf": "723940",
        "mosmix": null,
        "icao": "KSMX",
        "iata": null
    },
    "location": {
        "latitude": 34.9,
        "longitude": -120.4667,
        "elevation": 79
    },
    "timezone": "America\/Los_Angeles",
    "history": []
}