{
    "id": "72402",
    "name": {
        "en": "Wallops Flight Fac Airport"
    },
    "country": "US",
    "region": "VA",
    "identifiers": {
        "national": null,
        "wmo": "72402",
        "ghcn": "USW00093739",
        "wban": "93739",
        "usaf": "724020",
        "mosmix": null,
        "icao": "KWAL",
        "iata": null
    },
    "location": {
        "latitude": 37.9333,
        "longitude": -75.4667,
        "elevation": 12
    },
    "timezone": "America\/New_York",
    "history": []
}