{
    "id": "72641",
    "name": {
        "en": "Madison Dane County Rgnl"
    },
    "country": "US",
    "region": "WI",
    "identifiers": {
        "national": null,
        "wmo": "72641",
        "ghcn": "USW00014837",
        "wban": "14837",
        "usaf": "726410",
        "mosmix": null,
        "icao": "KMSN",
        "iata": "MSN"
    },
    "location": {
        "latitude": 43.1333,
        "longitude": -89.0167,
        "elevation": 263
    },
    "timezone": "America\/Chicago",
    "history": []
}