{
    "id": "80421",
    "name": {
        "en": "Porlamar Aero-Puerto International Del Caribe"
    },
    "country": "VE",
    "region": "O",
    "identifiers": {
        "national": null,
        "wmo": "80421",
        "ghcn": "VEM00080421",
        "wban": null,
        "usaf": null,
        "mosmix": "80421",
        "icao": null,
        "iata": "PMV"
    },
    "location": {
        "latitude": 10.9167,
        "longitude": -63.9667,
        "elevation": 24
    },
    "timezone": "America\/Caracas",
    "history": []
}