{
    "id": "84658",
    "name": {
        "en": "Puerto Maldonado"
    },
    "country": "PE",
    "region": "MD",
    "identifiers": {
        "national": null,
        "wmo": "84658",
        "ghcn": "PEM00084658",
        "wban": null,
        "usaf": "846580",
        "mosmix": null,
        "icao": "SPTU",
        "iata": "PEM"
    },
    "location": {
        "latitude": -12.6333,
        "longitude": -69.2,
        "elevation": 265
    },
    "timezone": "America\/Lima",
    "history": []
}