{
    "id": "87596",
    "name": {
        "en": "Punta Indio B. A."
    },
    "country": "AR",
    "region": "B",
    "identifiers": {
        "national": null,
        "wmo": "87596",
        "ghcn": "ARM00087596",
        "wban": null,
        "usaf": null,
        "mosmix": null,
        "icao": null,
        "iata": null
    },
    "location": {
        "latitude": -35.3667,
        "longitude": -57.2833,
        "elevation": 16
    },
    "timezone": "America\/Argentina\/Buenos_Aires",
    "history": []
}