{
    "id": "92076",
    "name": {
        "en": "Kavieng \/ Maiom"
    },
    "country": "PG",
    "region": "NI",
    "identifiers": {
        "national": null,
        "wmo": "92076",
        "ghcn": "PPM00092076",
        "wban": "80516",
        "usaf": null,
        "mosmix": null,
        "icao": "AYKV",
        "iata": "KVG"
    },
    "location": {
        "latitude": -2.5833,
        "longitude": 150.85,
        "elevation": 4
    },
    "timezone": "Pacific\/Port_Moresby",
    "history": []
}