{
    "id": "94356",
    "name": {
        "en": "Charters Towers Airport"
    },
    "country": "AU",
    "region": "QLD",
    "identifiers": {
        "national": null,
        "wmo": "94356",
        "ghcn": "ASN00034084",
        "wban": "82401",
        "usaf": null,
        "mosmix": null,
        "icao": "YCHT",
        "iata": "CXT"
    },
    "location": {
        "latitude": -20.0333,
        "longitude": 146.2667,
        "elevation": 291
    },
    "timezone": "Australia/Brisbane",
    "history": []
}