{
    "id": "94750",
    "name": {
        "en": "Nowra Ran Air Station"
    },
    "country": "AU",
    "region": "NSW",
    "identifiers": {
        "national": null,
        "wmo": "94750",
        "ghcn": "ASN00068072",
        "wban": null,
        "usaf": "947500",
        "mosmix": null,
        "icao": "YSNW",
        "iata": "NOA"
    },
    "location": {
        "latitude": -34.95,
        "longitude": 150.5333,
        "elevation": 122
    },
    "timezone": "Australia\/Sydney",
    "history": []
}