{
    "id": "95293",
    "name": {
        "en": "Woolshed \/ Alice River"
    },
    "country": "AU",
    "region": "QLD",
    "identifiers": {
        "national": null,
        "wmo": "95293",
        "ghcn": "ASN00033307",
        "wban": null,
        "usaf": null,
        "mosmix": null,
        "icao": null,
        "iata": null
    },
    "location": {
        "latitude": -19.4167,
        "longitude": 146.5364,
        "elevation": 556
    },
    "timezone": "Australia\/Brisbane",
    "history": []
}