{
    "id": "95675",
    "name": {
        "en": "Black Pole \/ Saint Kilda"
    },
    "country": "AU",
    "region": "SA",
    "identifiers": {
        "national": null,
        "wmo": "95675",
        "ghcn": null,
        "wban": null,
        "usaf": null,
        "mosmix": null,
        "icao": null,
        "iata": null
    },
    "location": {
        "latitude": -34.7342,
        "longitude": 138.4653,
        "elevation": 8
    },
    "timezone": "Australia\/Adelaide",
    "history": []
}