{
    "id": "CYJZ0",
    "name": {
        "en": "Allison Pass \/ Copper Mountain"
    },
    "country": "CA",
    "region": "BC",
    "identifiers": {
        "national": null,
        "wmo": null,
        "ghcn": null,
        "wban": "94233",
        "usaf": null,
        "mosmix": null,
        "icao": "CYJZ",
        "iata": null
    },
    "location": {
        "latitude": 49.1333,
        "longitude": -120.8333,
        "elevation": 1341
    },
    "timezone": "America\/Los_Angeles",
    "history": []
}