{
    "id": "EDAG0",
    "name": {
        "en": "Großrückerswalde \/ Grossruckerswalde \/ Grobruckerswalde [MISSPELLING] \/ Wolfsberg"
    },
    "country": "DE",
    "region": "SN",
    "identifiers": {
        "national": null,
        "wmo": null,
        "ghcn": null,
        "wban": null,
        "usaf": null,
        "mosmix": null,
        "icao": "EDAG",
        "iata": null
    },
    "location": {
        "latitude": 50.6442,
        "longitude": 13.1264,
        "elevation": 670
    },
    "timezone": "Europe\/Berlin",
    "history": []
}