{
    "id": "EDEW0",
    "name": {
        "en": "Wallduern / Walldurn / Walldürn"
    },
    "country": "DE",
    "region": "BW",
    "identifiers": {
        "national": null,
        "wmo": null,
        "ghcn": null,
        "wban": null,
        "usaf": "107635",
        "mosmix": null,
        "icao": "EDEW",
        "iata": null
    },
    "location": {
        "latitude": 49.5828,
        "longitude": 9.4033,
        "elevation": 400
    },
    "timezone": "Europe/Berlin",
    "history": []
}