{
    "id": "EDTX0",
    "name": {
        "en": "Schwaebisch Hall \/ Schwabisch Hall \/ Schwabish Hall \/ Altenhausen"
    },
    "country": "DE",
    "region": "BW",
    "identifiers": {
        "national": null,
        "wmo": null,
        "ghcn": null,
        "wban": null,
        "usaf": null,
        "mosmix": null,
        "icao": "EDTX",
        "iata": null
    },
    "location": {
        "latitude": 49.1192,
        "longitude": 9.7786,
        "elevation": 399
    },
    "timezone": "Europe\/Berlin",
    "history": []
}