{
    "id": "EGKE0",
    "name": {
        "en": "Challock Airfield \/ Charing"
    },
    "country": "GB",
    "region": "ENG",
    "identifiers": {
        "national": null,
        "wmo": null,
        "ghcn": null,
        "wban": null,
        "usaf": null,
        "mosmix": null,
        "icao": "EGKE",
        "iata": null
    },
    "location": {
        "latitude": 51.2083,
        "longitude": 0.8292,
        "elevation": 183
    },
    "timezone": "Europe\/London",
    "history": []
}