{
    "id": "ESGI0",
    "name": {
        "en": "Alingsås / Alingsas / Bälinge"
    },
    "country": "SE",
    "region": "Q",
    "identifiers": {
        "national": null,
        "wmo": null,
        "ghcn": null,
        "wban": null,
        "usaf": "023130",
        "mosmix": null,
        "icao": "ESGI",
        "iata": null
    },
    "location": {
        "latitude": 57.9498,
        "longitude": 12.578,
        "elevation": 56
    },
    "timezone": "Europe/Stockholm",
    "history": []
}