{
    "id": "FLWW0",
    "name": {
        "en": "Waka Waka \/ Wakawaka \/ Chipuka"
    },
    "country": "ZM",
    "region": "ES",
    "identifiers": {
        "national": null,
        "wmo": null,
        "ghcn": null,
        "wban": null,
        "usaf": null,
        "mosmix": null,
        "icao": "FLWW",
        "iata": null
    },
    "location": {
        "latitude": -12.4504,
        "longitude": 32.257,
        "elevation": 549
    },
    "timezone": "Africa\/Lusaka",
    "history": []
}