{
    "id": "FMML0",
    "name": {
        "en": "Belo sur Tsiribihina / Belo Tsiribihina"
    },
    "country": "MG",
    "region": "U",
    "identifiers": {
        "national": null,
        "wmo": null,
        "ghcn": null,
        "wban": null,
        "usaf": null,
        "mosmix": null,
        "icao": "FMML",
        "iata": "BMD"
    },
    "location": {
        "latitude": -19.6867,
        "longitude": 44.5419,
        "elevation": 47
    },
    "timezone": "Indian/Antananarivo",
    "history": []
}