{
    "id": "HKLK0",
    "name": {
        "en": "Lokichoggio \/ Lokichogio \/ Lokichokio"
    },
    "country": "KE",
    "region": "RV",
    "identifiers": {
        "national": null,
        "wmo": null,
        "ghcn": null,
        "wban": null,
        "usaf": null,
        "mosmix": null,
        "icao": "HKLK",
        "iata": "LKG"
    },
    "location": {
        "latitude": 4.2041,
        "longitude": 34.3482,
        "elevation": 632
    },
    "timezone": "Africa\/Nairobi",
    "history": []
}