{
    "id": "K01E0",
    "name": {
        "en": "Angola / Lake James"
    },
    "country": "US",
    "region": "IN",
    "identifiers": {
        "national": null,
        "wmo": null,
        "ghcn": null,
        "wban": null,
        "usaf": null,
        "mosmix": null,
        "icao": "K01E",
        "iata": null
    },
    "location": {
        "latitude": 41.7,
        "longitude": -85.0393,
        "elevation": 294
    },
    "timezone": "America/Indiana/Indianapolis",
    "history": []
}