{
    "id": "K1F60",
    "name": {
        "en": "Dolgeville \/ Doxtater Corner"
    },
    "country": "US",
    "region": "NY",
    "identifiers": {
        "national": null,
        "wmo": null,
        "ghcn": null,
        "wban": null,
        "usaf": null,
        "mosmix": null,
        "icao": "K1F6",
        "iata": null
    },
    "location": {
        "latitude": 43.1167,
        "longitude": -74.7496,
        "elevation": 288
    },
    "timezone": "America\/New_York",
    "history": []
}