{
    "id": "K4Y10",
    "name": {
        "en": "Howell / Sylvan Glen Mobile Estates"
    },
    "country": "US",
    "region": "MI",
    "identifiers": {
        "national": null,
        "wmo": null,
        "ghcn": null,
        "wban": null,
        "usaf": null,
        "mosmix": null,
        "icao": "K4Y1",
        "iata": null
    },
    "location": {
        "latitude": 42.5652,
        "longitude": -83.8563,
        "elevation": 299
    },
    "timezone": "America/Detroit",
    "history": []
}