{
    "id": "K7K80",
    "name": {
        "en": "South Sioux City \/ Millis Beach"
    },
    "country": "US",
    "region": "NE",
    "identifiers": {
        "national": null,
        "wmo": null,
        "ghcn": null,
        "wban": null,
        "usaf": null,
        "mosmix": null,
        "icao": "K7K8",
        "iata": null
    },
    "location": {
        "latitude": 42.4542,
        "longitude": -96.4725,
        "elevation": 335
    },
    "timezone": "America\/Chicago",
    "history": []
}