{
    "id": "KCGE0",
    "name": {
        "en": "Cambridge \/ Thompson"
    },
    "country": "US",
    "region": "MD",
    "identifiers": {
        "national": null,
        "wmo": null,
        "ghcn": null,
        "wban": "00356",
        "usaf": "722218",
        "mosmix": null,
        "icao": "KCGE",
        "iata": null
    },
    "location": {
        "latitude": 38.5393,
        "longitude": -76.0304,
        "elevation": 6
    },
    "timezone": "America\/New_York",
    "history": []
}