{
    "id": "KCSL0",
    "name": {
        "en": "San Luis Obispo \/ Goldtree"
    },
    "country": "US",
    "region": "CA",
    "identifiers": {
        "national": null,
        "wmo": null,
        "ghcn": null,
        "wban": null,
        "usaf": null,
        "mosmix": null,
        "icao": "KCSL",
        "iata": null
    },
    "location": {
        "latitude": 35.3333,
        "longitude": -120.7343,
        "elevation": 76
    },
    "timezone": "America\/Los_Angeles",
    "history": []
}