{
    "id": "KDLZ0",
    "name": {
        "en": "Delaware \/ Sunnyview Farms"
    },
    "country": "US",
    "region": "OH",
    "identifiers": {
        "national": null,
        "wmo": null,
        "ghcn": null,
        "wban": "00315",
        "usaf": "720928",
        "mosmix": null,
        "icao": "KDLZ",
        "iata": null
    },
    "location": {
        "latitude": 40.2797,
        "longitude": -83.1148,
        "elevation": 288
    },
    "timezone": "America\/New_York",
    "history": []
}