{
    "id": "KFKA0",
    "name": {
        "en": "Preston \/ Carimona"
    },
    "country": "US",
    "region": "MN",
    "identifiers": {
        "national": null,
        "wmo": null,
        "ghcn": null,
        "wban": "04927",
        "usaf": "720283",
        "mosmix": null,
        "icao": "KFKA",
        "iata": null
    },
    "location": {
        "latitude": 43.6767,
        "longitude": -92.1797,
        "elevation": 389
    },
    "timezone": "America\/Chicago",
    "history": []
}