{
    "id": "KI220",
    "name": {
        "en": "Winchester / Harrisville"
    },
    "country": "US",
    "region": "IN",
    "identifiers": {
        "national": null,
        "wmo": null,
        "ghcn": null,
        "wban": null,
        "usaf": null,
        "mosmix": null,
        "icao": "KI22",
        "iata": null
    },
    "location": {
        "latitude": 40.1689,
        "longitude": -84.9257,
        "elevation": 342
    },
    "timezone": "America/Indiana/Indianapolis",
    "history": []
}