{
    "id": "KIPJ0",
    "name": {
        "en": "Lincolnton / Goodsonville"
    },
    "country": "US",
    "region": "NC",
    "identifiers": {
        "national": null,
        "wmo": null,
        "ghcn": null,
        "wban": "53899",
        "usaf": "722128",
        "mosmix": null,
        "icao": "KIPJ",
        "iata": null
    },
    "location": {
        "latitude": 35.4833,
        "longitude": -81.1612,
        "elevation": 267
    },
    "timezone": "America/New_York",
    "history": []
}