{
    "id": "KMRJ0",
    "name": {
        "en": "Mineral Point / Linden"
    },
    "country": "US",
    "region": "WI",
    "identifiers": {
        "national": null,
        "wmo": null,
        "ghcn": null,
        "wban": "54907",
        "usaf": "726507",
        "mosmix": null,
        "icao": "KMRJ",
        "iata": null
    },
    "location": {
        "latitude": 42.8868,
        "longitude": -90.2362,
        "elevation": 357
    },
    "timezone": "America/Chicago",
    "history": []
}