{
    "id": "KN680",
    "name": {
        "en": "Chambersburg \/ Red Bridge"
    },
    "country": "US",
    "region": "PA",
    "identifiers": {
        "national": null,
        "wmo": null,
        "ghcn": null,
        "wban": null,
        "usaf": null,
        "mosmix": null,
        "icao": "KN68",
        "iata": null
    },
    "location": {
        "latitude": 39.973,
        "longitude": -77.6433,
        "elevation": 210
    },
    "timezone": "America\/New_York",
    "history": []
}