{
    "id": "KP140",
    "name": {
        "en": "Holbrook \/ Lisitzky Subdivision"
    },
    "country": "US",
    "region": "AZ",
    "identifiers": {
        "national": null,
        "wmo": null,
        "ghcn": null,
        "wban": null,
        "usaf": null,
        "mosmix": null,
        "icao": "KP14",
        "iata": null
    },
    "location": {
        "latitude": 34.9405,
        "longitude": -110.1382,
        "elevation": 1604
    },
    "timezone": "America\/Phoenix",
    "history": []
}