{
    "id": "KS690",
    "name": {
        "en": "Lincoln / Huckleberry Trailer Court"
    },
    "country": "US",
    "region": "MT",
    "identifiers": {
        "national": null,
        "wmo": null,
        "ghcn": null,
        "wban": null,
        "usaf": null,
        "mosmix": null,
        "icao": "KS69",
        "iata": null
    },
    "location": {
        "latitude": 46.9547,
        "longitude": -112.6502,
        "elevation": 1403
    },
    "timezone": "America/Denver",
    "history": []
}