{
    "id": "KTMT0",
    "name": {
        "en": "Austin / Jacobsville (Historical)"
    },
    "country": "US",
    "region": "NV",
    "identifiers": {
        "national": null,
        "wmo": null,
        "ghcn": null,
        "wban": null,
        "usaf": "720129",
        "mosmix": null,
        "icao": "KTMT",
        "iata": null
    },
    "location": {
        "latitude": 39.468,
        "longitude": -117.1954,
        "elevation": 1748
    },
    "timezone": "America/Los_Angeles",
    "history": []
}