{
    "id": "KW100",
    "name": {
        "en": "Langley \/ Wheel Estates Mobile Home Park"
    },
    "country": "US",
    "region": "WA",
    "identifiers": {
        "national": null,
        "wmo": null,
        "ghcn": null,
        "wban": null,
        "usaf": null,
        "mosmix": null,
        "icao": "KW10",
        "iata": null
    },
    "location": {
        "latitude": 48.0175,
        "longitude": -122.4377,
        "elevation": 83
    },
    "timezone": "America\/Los_Angeles",
    "history": []
}