{
    "id": "KW240",
    "name": {
        "en": "Lynchburg / Jackson Heights"
    },
    "country": "US",
    "region": "VA",
    "identifiers": {
        "national": null,
        "wmo": null,
        "ghcn": null,
        "wban": null,
        "usaf": null,
        "mosmix": null,
        "icao": "KW24",
        "iata": null
    },
    "location": {
        "latitude": 37.3779,
        "longitude": -79.1222,
        "elevation": 286
    },
    "timezone": "America/New_York",
    "history": []
}