{
    "id": "LFCE0",
    "name": {
        "en": "Guéret St Laurent / Gueret-Saint-Laurent / Bordessoule"
    },
    "country": "FR",
    "region": "L",
    "identifiers": {
        "national": null,
        "wmo": null,
        "ghcn": null,
        "wban": null,
        "usaf": null,
        "mosmix": null,
        "icao": "LFCE",
        "iata": "XGT"
    },
    "location": {
        "latitude": 46.1792,
        "longitude": 1.9583,
        "elevation": 368
    },
    "timezone": "Europe/Paris",
    "history": []
}