{
    "id": "LFDE0",
    "name": {
        "en": "Égletons \/ Egletons \/ Le Bouchard"
    },
    "country": "FR",
    "region": "L",
    "identifiers": {
        "national": null,
        "wmo": null,
        "ghcn": null,
        "wban": null,
        "usaf": null,
        "mosmix": null,
        "icao": "LFDE",
        "iata": null
    },
    "location": {
        "latitude": 45.4214,
        "longitude": 2.0689,
        "elevation": 566
    },
    "timezone": "Europe\/Paris",
    "history": []
}