{
    "id": "LFIB0",
    "name": {
        "en": "Belvès St Pardoux / Belves-Saint-Pardoux / La Salvagie"
    },
    "country": "FR",
    "region": "B",
    "identifiers": {
        "national": null,
        "wmo": null,
        "ghcn": null,
        "wban": null,
        "usaf": null,
        "mosmix": null,
        "icao": "LFIB",
        "iata": null
    },
    "location": {
        "latitude": 44.7825,
        "longitude": 0.9589,
        "elevation": 241
    },
    "timezone": "Europe/Paris",
    "history": []
}