{
    "id": "LFIY0",
    "name": {
        "en": "St Jean D'angély \/ Saint Jean D'angely Saint Denis Du Pin \/ Saint-Jean-d'Angély"
    },
    "country": "FR",
    "region": "T",
    "identifiers": {
        "national": null,
        "wmo": null,
        "ghcn": null,
        "wban": null,
        "usaf": null,
        "mosmix": null,
        "icao": "LFIY",
        "iata": null
    },
    "location": {
        "latitude": 45.9664,
        "longitude": -0.5253,
        "elevation": 75
    },
    "timezone": "Europe\/Paris",
    "history": []
}