{
    "id": "LOAW0",
    "name": {
        "en": "Öamtc / Oamtc / Theresienfeld"
    },
    "country": "AT",
    "region": "NO",
    "identifiers": {
        "national": null,
        "wmo": null,
        "ghcn": null,
        "wban": null,
        "usaf": null,
        "mosmix": null,
        "icao": "LOAW",
        "iata": null
    },
    "location": {
        "latitude": 47.8456,
        "longitude": 16.2528,
        "elevation": 274
    },
    "timezone": "Europe/Vienna",
    "history": []
}