{
    "id": "LSPH0",
    "name": {
        "en": "Winterthur  / Oberwinterthur (Kreis 2)"
    },
    "country": "CH",
    "region": "ZH",
    "identifiers": {
        "national": null,
        "wmo": null,
        "ghcn": null,
        "wban": null,
        "usaf": null,
        "mosmix": null,
        "icao": "LSPH",
        "iata": null
    },
    "location": {
        "latitude": 47.5167,
        "longitude": 8.7667,
        "elevation": 460
    },
    "timezone": "Europe/Zurich",
    "history": []
}