{
    "id": "MGUA0",
    "name": {
        "en": "Guatemala City / Villa Nueva"
    },
    "country": "GT",
    "region": "GU",
    "identifiers": {
        "national": null,
        "wmo": null,
        "ghcn": null,
        "wban": "11901",
        "usaf": null,
        "mosmix": null,
        "icao": "MGUA",
        "iata": null
    },
    "location": {
        "latitude": 14.5333,
        "longitude": -90.5667,
        "elevation": 1496
    },
    "timezone": "America/Guatemala",
    "history": []
}