{
    "id": "PBAR0",
    "name": {
        "en": "Baker Island AAF \/ Meyerton pre-WW2"
    },
    "country": "UM",
    "region": "UM",
    "identifiers": {
        "national": null,
        "wmo": null,
        "ghcn": null,
        "wban": "20701",
        "usaf": null,
        "mosmix": null,
        "icao": "PBAR",
        "iata": null
    },
    "location": {
        "latitude": 0.2167,
        "longitude": -176.4667,
        "elevation": 3
    },
    "timezone": "Pacific\/Midway",
    "history": []
}