{
    "id": "PFNO0",
    "name": {
        "en": "Noorvik / Andrewsville"
    },
    "country": "US",
    "region": "AK",
    "identifiers": {
        "national": null,
        "wmo": null,
        "ghcn": null,
        "wban": "00113",
        "usaf": "704898",
        "mosmix": null,
        "icao": "PFNO",
        "iata": null
    },
    "location": {
        "latitude": 38.8495,
        "longitude": -75.6128,
        "elevation": 20
    },
    "timezone": "America/New_York",
    "history": []
}