{
    "id": "SHVM0",
    "name": {
        "en": "Cartagena / Los Maitenes"
    },
    "country": "CL",
    "region": "VS",
    "identifiers": {
        "national": null,
        "wmo": null,
        "ghcn": null,
        "wban": null,
        "usaf": null,
        "mosmix": null,
        "icao": "SHVM",
        "iata": null
    },
    "location": {
        "latitude": -33.4694,
        "longitude": -71.3992,
        "elevation": 250
    },
    "timezone": "America/Santiago",
    "history": []
}