{
    "id": "TUPA0",
    "name": {
        "en": "Captain Auguste George \/ The Settlement"
    },
    "country": "VG",
    "region": null,
    "identifiers": {
        "national": null,
        "wmo": null,
        "ghcn": null,
        "wban": null,
        "usaf": null,
        "mosmix": null,
        "icao": "TUPA",
        "iata": "NGD"
    },
    "location": {
        "latitude": 18.7272,
        "longitude": -64.3297,
        "elevation": 3
    },
    "timezone": "America\/Tortola",
    "history": []
}