{
    "id": "UWOO0",
    "name": {
        "en": "Trudovoye Pole / Orenberg"
    },
    "country": "RU",
    "region": "ORE",
    "identifiers": {
        "national": null,
        "wmo": null,
        "ghcn": null,
        "wban": null,
        "usaf": "351210",
        "mosmix": null,
        "icao": "UWOO",
        "iata": "REN"
    },
    "location": {
        "latitude": 51.7833,
        "longitude": 55.45,
        "elevation": 118
    },
    "timezone": "Asia/Yekaterinburg",
    "history": []
}